xlttools/__init__.py
xlttools/test.py
xlttools-0.0.2.dist-info/LICENSE
xlttools-0.0.2.dist-info/METADATA
xlttools-0.0.2.dist-info/WHEEL
xlttools-0.0.2.dist-info/top_level.txt
xlttools-0.0.2.dist-info/RECORD
