Metadata-Version: 2.1
Name: xlttools
Version: 0.0.2
Summary: This is a tool library of x1aolata.
Home-page: https://github.com/x1aolata/xlttools
Author: x1aolata
Author-email: 2542060010@qq.com
License: MIT license
Project-URL: Bug Tracker,  https://github.com/x1aolata/xlttools/issues
Platform: UNKNOWN
Requires-Python: >=3.6
License-File: LICENSE
Requires-Dist: numpy
